project_tooling_commons/__init__.py
project_tooling_commons/base.py
project_tooling_commons/logger.py
project_tooling_commons-0.0.9.dist-info/AUTHORS.rst
project_tooling_commons-0.0.9.dist-info/LICENSE.txt
project_tooling_commons-0.0.9.dist-info/METADATA
project_tooling_commons-0.0.9.dist-info/WHEEL
project_tooling_commons-0.0.9.dist-info/top_level.txt
project_tooling_commons-0.0.9.dist-info/RECORD
